ominix_tts/__init__.py
ominix_tts/export_torch_script.py
ominix_tts/export_torch_script_v3.py
ominix_tts/model_download.py
ominix_tts/onnx_export.py
ominix_tts/pipeline.py
ominix_tts/process_ckpt.py
ominix_tts/utils.py
ominix_tts/AR/__init__.py
ominix_tts/AR/data/__init__.py
ominix_tts/AR/data/bucket_sampler.py
ominix_tts/AR/data/data_module.py
ominix_tts/AR/data/dataset.py
ominix_tts/AR/models/__init__.py
ominix_tts/AR/models/t2s_lightning_module.py
ominix_tts/AR/models/t2s_lightning_module_onnx.py
ominix_tts/AR/models/t2s_model.py
ominix_tts/AR/models/t2s_model_onnx.py
ominix_tts/AR/models/utils.py
ominix_tts/AR/modules/__init__.py
ominix_tts/AR/modules/activation.py
ominix_tts/AR/modules/activation_onnx.py
ominix_tts/AR/modules/embedding.py
ominix_tts/AR/modules/embedding_onnx.py
ominix_tts/AR/modules/lr_schedulers.py
ominix_tts/AR/modules/optim.py
ominix_tts/AR/modules/patched_mha_with_cache.py
ominix_tts/AR/modules/patched_mha_with_cache_onnx.py
ominix_tts/AR/modules/scaling.py
ominix_tts/AR/modules/transformer.py
ominix_tts/AR/modules/transformer_onnx.py
ominix_tts/AR/text_processing/__init__.py
ominix_tts/AR/text_processing/phonemizer.py
ominix_tts/AR/text_processing/symbols.py
ominix_tts/AR/utils/__init__.py
ominix_tts/AR/utils/initialize.py
ominix_tts/AR/utils/io.py
ominix_tts/audio_synthesis/__init__.py
ominix_tts/audio_synthesis/audio_processor.py
ominix_tts/audio_synthesis/base_synthesizer.py
ominix_tts/audio_synthesis/synthesizer_factory.py
ominix_tts/audio_synthesis/vits_synthesizer.py
ominix_tts/audio_synthesis/vits_v3_synthesizer.py
ominix_tts/dataset/__init__.py
ominix_tts/dataset/doubao-ref-ours.wav
ominix_tts/dataset/doubao-ref.txt
ominix_tts/f5_tts/__init__.py
ominix_tts/f5_tts/model/__init__.py
ominix_tts/f5_tts/model/modules.py
ominix_tts/f5_tts/model/backbones/__init__.py
ominix_tts/f5_tts/model/backbones/dit.py
ominix_tts/f5_tts/model/backbones/mmdit.py
ominix_tts/f5_tts/model/backbones/unett.py
ominix_tts/feature_extractor/__init__.py
ominix_tts-0.1.0.dist-info/licenses/LICENSE
ominix_tts-0.1.0.dist-info/METADATA
ominix_tts-0.1.0.dist-info/WHEEL
ominix_tts-0.1.0.dist-info/top_level.txt
ominix_tts-0.1.0.dist-info/RECORD
