Metadata-Version: 2.4
Name: ominix-tts
Version: 0.1.0
Summary: Ominix TTS: A multilingual TTS system
Home-page: https://github.com/cshbli/Ominix-TTS
Author: Hongbing Li
Author-email: Hongbing Li <cshbli@hotmail.com>
License: MIT License
Project-URL: Homepage, https://github.com/cshbli/Ominix-TTS
Classifier: Programming Language :: Python :: 3
Classifier: License :: OSI Approved :: MIT License
Classifier: Operating System :: OS Independent
Requires-Python: >=3.9
License-File: LICENSE
Requires-Dist: cn2an
Requires-Dist: fast_langdetect>=0.3.0
Requires-Dist: ffmpeg-python
Requires-Dist: g2p_en
Requires-Dist: gradio<=4.24.0,>=4.0
Requires-Dist: huggingface_hub>=0.13
Requires-Dist: jieba
Requires-Dist: jieba_fast
Requires-Dist: librosa>=0.9.2
Requires-Dist: matplotlib
Requires-Dist: numpy<2.0.0,>=1.23.4
Requires-Dist: peft
Requires-Dist: pypinyin
Requires-Dist: pytorch-lightning>2.0
Requires-Dist: split-lang
Requires-Dist: torchaudio
Requires-Dist: tqdm
Requires-Dist: transformers>=4.43
Requires-Dist: wordsegment
Requires-Dist: x_transformers
Dynamic: author
Dynamic: home-page
Dynamic: license-file
Dynamic: requires-python
